transcribe_zh_en/__init__.py
transcribe_zh_en/audio_to_text.py
transcribe_zh_en/main.py
transcribe_zh_en-1.5.dist-info/LICENSE
transcribe_zh_en-1.5.dist-info/METADATA
transcribe_zh_en-1.5.dist-info/WHEEL
transcribe_zh_en-1.5.dist-info/entry_points.txt
transcribe_zh_en-1.5.dist-info/top_level.txt
transcribe_zh_en-1.5.dist-info/RECORD
