Metadata-Version: 2.1
Name: transcribe-zh-en
Version: 1.5
Summary: A package to transcribe Chinese subtitles and remove audio from videos
Home-page: https://github.com/Abdulhamid97Mousa/transcribe_zh_en
Author: Mousa Abdulhamid
Author-email: mousa.abdulhamid97@gmail.com
License: UNKNOWN
Platform: UNKNOWN
Classifier: Programming Language :: Python :: 3
Classifier: License :: OSI Approved :: MIT License
Classifier: Operating System :: OS Independent
Requires-Dist: ffmpeg-python==0.2.0
Requires-Dist: paddlespeech==1.4.2
Requires-Dist: paddlepaddle-gpu==2.5.1
Requires-Dist: numpy==1.23.5
